AUTHORS.rst
CHANGELOG.rst
CONTRIBUTING.md
LICENSE
README.rst
docs/Makefile
docs/conf.py
docs/index.rst
scdlbot/scdlbot.py
scdlbot/texts/direct_restriction.txt
scdlbot/texts/dl_timeout.txt
scdlbot/texts/failed.txt
scdlbot/texts/help.tg.md
scdlbot/texts/live_restriction.txt
scdlbot/texts/no_urls.txt
scdlbot/texts/not_admin.txt
scdlbot/texts/old_msg.txt
scdlbot/texts/region_restriction.txt
scdlbot/texts/settings.tg.md
scdlbot/texts/wait_beat.txt
scdlbot/texts/wait_beet.txt
scdlbot/texts/wait_bit.txt
scdlbot-0.15.0.dist-info/LICENSE
scdlbot-0.15.0.dist-info/WHEEL
scdlbot-0.15.0.dist-info/METADATA
scdlbot-0.15.0.dist-info/entry_points.txt
scdlbot-0.15.0.dist-info/RECORD
