Metadata-Version: 2.1
Name: scdlbot
Version: 0.15.0
Summary: Telegram Bot for downloading MP3 rips of tracks/sets from SoundCloud, Bandcamp, YouTube with tags and artwork
Home-page: https://github.com/gpchelkin/scdlbot
License: MIT
Keywords: scdlbot,telegram,bot,soundcloud,bandcamp,youtube,mixcloud,yandex,audio,music,download
Author: George Pchelkin
Author-email: george@pchelk.in
Requires-Python: >=3.9,<4.0
Classifier: Development Status :: 4 - Beta
Classifier: Intended Audience :: Developers
Classifier: Intended Audience :: System Administrators
Classifier: License :: OSI Approved :: MIT License
Classifier: Natural Language :: English
Classifier: Operating System :: OS Independent
Classifier: Programming Language :: Python :: 3
Classifier: Programming Language :: Python :: 3.9
Classifier: Programming Language :: Python :: 3.10
Classifier: Programming Language :: Python :: 3.11
Classifier: Topic :: Internet
Classifier: Topic :: Multimedia :: Sound/Audio
Requires-Dist: bandcamp-downloader (==0.0.13)
Requires-Dist: boltons (>=21.0.0,<22.0.0)
Requires-Dist: fake-useragent (>=1.1.1,<2.0.0)
Requires-Dist: ffmpeg-python (==0.2.0)
Requires-Dist: mutagen (>=1.46.0,<2.0.0)
Requires-Dist: plumbum (>=1.8.1,<2.0.0)
Requires-Dist: prometheus_client (>=0.16.0,<0.17.0)
Requires-Dist: python-telegram-bot[job-queue,webhooks] (==20.1)
Requires-Dist: requests[socks] (>=2.28.2,<3.0.0)
Requires-Dist: scdl (==2.7.3)
Requires-Dist: sdnotify (>=0.3.2,<0.4.0)
Requires-Dist: yt-dlp (==2023.2.17)
Project-URL: CI, https://github.com/gpchelkin/scdlbot/actions
Project-URL: Changelog, https://github.com/gpchelkin/scdlbot/releases
Project-URL: Documentation, https://scdlbot.readthedocs.io
Project-URL: Issues, https://github.com/gpchelkin/scdlbot/issues
Project-URL: Repository, https://github.com/gpchelkin/scdlbot
